{
	"configurations" : 
	[
		{
			"directories" : 
			[
				{
					"build" : ".",
					"jsonFile" : "directory-.-Debug-d0094a50bb2071803777.json",
					"minimumCMakeVersion" : 
					{
						"string" : "3.27"
					},
					"projectIndex" : 0,
					"source" : ".",
					"targetIndexes" : 
					[
						0
					]
				}
			],
			"name" : "Debug",
			"projects" : 
			[
				{
					"directoryIndexes" : 
					[
						0
					],
					"name" : "swapp_letters_greedy",
					"targetIndexes" : 
					[
						0
					]
				}
			],
			"targets" : 
			[
				{
					"directoryIndex" : 0,
					"id" : "swapp_letters_greedy::@6890427a1f51a3e7e1df",
					"jsonFile" : "target-swapp_letters_greedy-Debug-a91b216c9ddf15131ceb.json",
					"name" : "swapp_letters_greedy",
					"projectIndex" : 0
				}
			]
		}
	],
	"kind" : "codemodel",
	"paths" : 
	{
		"build" : "C:/Users/esteb/OneDrive/Escritorio/algo3/swapp_letters_greedy/cmake-build-debug",
		"source" : "C:/Users/esteb/OneDrive/Escritorio/algo3/swapp_letters_greedy"
	},
	"version" : 
	{
		"major" : 2,
		"minor" : 6
	}
}
